calculator_package/calculator.py
zversal_calculator_package-0.1.2.dist-info/METADATA
zversal_calculator_package-0.1.2.dist-info/WHEEL
zversal_calculator_package-0.1.2.dist-info/top_level.txt
zversal_calculator_package-0.1.2.dist-info/RECORD
